lofar_obs_xml-2.0.data/scripts/genvalobs
lofarobsxml/__init__.py
lofarobsxml/angles.py
lofarobsxml/backend.py
lofarobsxml/beam.py
lofarobsxml/folder.py
lofarobsxml/genxml.py
lofarobsxml/momformats.py
lofarobsxml/observation.py
lofarobsxml/observationspecificationbase.py
lofarobsxml/pipelines.py
lofarobsxml/sourcecatalogue.py
lofarobsxml/targetsource.py
lofarobsxml/utilities.py
momxml/__init__.py
momxml/angles.py
momxml/backend.py
momxml/beam.py
momxml/folder.py
momxml/genxml.py
momxml/momformats.py
momxml/observation.py
momxml/observationspecificationbase.py
momxml/pipelines.py
momxml/sourcecatalogue.py
momxml/targetsource.py
momxml/utilities.py
lofar_obs_xml-2.0.dist-info/LICENSE
lofar_obs_xml-2.0.dist-info/METADATA
lofar_obs_xml-2.0.dist-info/WHEEL
lofar_obs_xml-2.0.dist-info/top_level.txt
lofar_obs_xml-2.0.dist-info/RECORD
