Metadata-Version: 2.1
Name: lofar-obs-xml
Version: 2.0
Summary: Generate XML file with LOFAR system validation observations
Home-page: https://github.com/brentjens/lofar-obs-xml
Author: Michiel Brentjens
Author-email: brentjens@astron.nl
License: UNKNOWN
Platform: UNKNOWN
Classifier: Programming Language :: Python :: 3
Classifier: License :: OSI Approved :: GNU General Public License v3 (GPLv3)
Classifier: Operating System :: OS Independent
Requires: ephem
Requires-Python: >=3.6
